perkle/__init__.py
perkle/example.py
perkle/merkletree.py
perkle/tests.py
perkle/utils.py
perkle-0.0.5.dist-info/LICENSE
perkle-0.0.5.dist-info/METADATA
perkle-0.0.5.dist-info/WHEEL
perkle-0.0.5.dist-info/top_level.txt
perkle-0.0.5.dist-info/RECORD
